{
  "app_id": "1460605258072985705",
  "default": {
    "state": "Chilling",
    "details": "At the workspace",
    "large_text": "Arch Linux-zen x86_64",
    "large_image": "arch",
    "small_text": "Hyprland (Wayland)",
    "small_image": "hyprland"
  },
  "classes": {
    "kitty": {
      "state": "At kitty",
      "details": "Writing command lines",
      "large_text": "Arch Linux-zen x86_64",
      "large_image": "arch",
      "small_text": "Kitty with ZSH",
      "small_image": "kitty"
    }
  }
}
